{"cameraMode":{"drawMode":0,"name":"Shaded","section":"Shading Mode"},"sceneLighting":true,"audioPlay":false,"sceneViewState":{"m_AlwaysRefresh":false,"showFog":true,"showSkybox":true,"showFlares":true,"showImageEffects":true,"showParticleSystems":true,"showVisualEffectGraphs":true,"m_FxEnabled":true},"in2DMode":false,"pivot":{"x":2.363910675048828,"y":4.525643348693848,"z":4.679393768310547},"rotation":{"x":0.048340827226638797,"y":0.725584864616394,"z":-0.05123855546116829,"w":0.6845354437828064},"size":20.23128318786621,"orthographic":false}